Workbook

Sheet Competitive Landscape
A1: KAGAMI COMPETITIVE PRICING ANALYSIS
A3: Competitor | B3: Monthly Price | C3: Annual Price | D3: Annual Savings | E3: Key Features | F3: Market Position
A4: ChatGPT Plus | B4: 20 | C4: 200 | D4: =$B4*12-$C4 | E4: AI chat, GPT-4, DALL-E | F4: Mass market AI
A5: Claude Pro | B5: 20 | C5: 200 | D5: =$B5*12-$C5 | E5: AI chat, 200K context, artifacts | F5: Mass market AI
A6: Claude Max (5x) | B6: 100 | C6: N/A | D6: N/A | E6: 5x usage limits | F6: Power users
A7: Claude Max (20x) | B7: 200 | C7: N/A | D7: N/A | E7: 20x usage limits | F7: Heavy users
A8: Google Home Premium Std | B8: 10 | C8: 100 | D8: =$B8*12-$C8 | E8: Gemini, 30d video, smart home | F8: Smart home
A9: Google Home Premium Adv | B9: 20 | C9: 200 | D9: =$B9*12-$C9 | E9: AI cameras, Ask Home, search | F9: Smart home+
A10: Amazon Alexa+ | B10: 19.99 | C10: N/A | D10: Free w/Prime | E10: AI assistant, smart home | F10: Ecosystem
A11: KAGAMI Personal | B11: 9 | C11: 90 | D11: =$B11*12-$C11 | E11: AI + smart home + voice | F11: Value leader
A12: KAGAMI Family | B12: 19 | C12: 190 | D12: =$B12*12-$C12 | E12: 6 members, parental controls | F12: Family value
A13: KAGAMI Power | B13: 29 | C13: 290 | D13: =$B13*12-$C13 | E13: Unlimited + API + SLA | F13: Power users
A16: PRICE COMPARISON VS COMPETITORS
A18: Metric | B18: Value | C18: Notes
A19: Kagami vs ChatGPT (Personal) | B19: =B11/B4-1 | C19: 55% cheaper
A20: Kagami vs Claude Pro (Personal) | B20: =B11/B5-1 | C20: 55% cheaper
A21: Kagami vs Google Home Std | B21: =B11/B8-1 | C21: 10% cheaper
A22: Kagami Family vs Google Adv | B22: =B12/B9-1 | C22: 5% cheaper with 6 members
A23: Kagami Power vs Claude Max 5x | B23: =B13/B6-1 | C23: 71% cheaper

Sheet COGS Breakdown
A1: COST OF GOODS SOLD (COGS) ANALYSIS
A3: AI API COSTS (per operation)
A5: Component | B5: Tokens | C5: Price/M tokens | D5: Cost/Op | E5: Notes
A6: Input tokens (Claude Sonnet) | B6: 500 | C6: 3 | D6: =B6*C6/1000000 | E6: Average request
A7: Output tokens (Claude Sonnet) | B7: 500 | C7: 15 | D7: =B7*C7/1000000 | E7: Average response
A8: Total per AI operation | D8: =D6+D7 | E8: Without caching
A9: With 90% cache hit rate | D9: =D8*0.1+D8*0.9*0.1 | E9: Cached input is 90% off
A12: INFRASTRUCTURE COSTS (Cloud Run, per operation)
A14: Component | B14: Usage | C14: Unit | D14: Rate | E14: Cost/Op
A15: CPU | B15: 0.5 | C15: vCPU-sec | D15: 2.4e-05 | E15: =B15*D15
A16: Memory | B16: 0.5 | C16: GiB-sec | D16: 2.5e-06 | E16: =B16*D16
A17: Request | B17: 1 | C17: request | D17: 4e-07 | E17: =B17*D17
A18: Network egress | B18: 0.001 | C18: GB | D18: 0.12 | E18: =B18*D18
A19: Total Infrastructure/Op | E19: =SUM(E15:E18)
A22: COGS SUMMARY
A24: Scenario | B24: AI Cost/Op | C24: Infra Cost/Op | D24: Total/Op | E24: Per 1K Ops
A25: 100% AI operations (no cache) | B25: =D8 | C25: =E19 | D25: =B25+C25 | E25: =D25*1000
A26: 100% AI operations (90% cache) | B26: =D9 | C26: =E19 | D26: =B26+C26 | E26: =D26*1000
A27: 30% AI / 70% lightweight | B27: =D9*0.3 | C27: =E19 | D27: =B27+C27 | E27: =D27*1000
A28: 10% AI / 90% lightweight | B28: =D9*0.1 | C28: =E19 | D28: =B28+C28 | E28: =D28*1000
A31: KEY ASSUMPTIONS
A32: • Average tokens per operation: 500 input + 500 output
A33: • Cache hit rate: 90% (via Anthropic prompt caching)
A34: • Lightweight ops: smart home commands, queries (no AI)
A35: • Cloud Run: us-central1, CPU allocated during request
A36: • Request duration: 500ms average

Sheet Unit Economics
A1: UNIT ECONOMICS PER SUBSCRIPTION TIER
A3: ASSUMPTIONS (modify these to model scenarios)
A5: Parameter | B5: Value | C5: Notes
A6: AI operation ratio | B6: 0.3 | C6: % of ops requiring AI
A7: Cache hit rate | B7: 0.9 | C7: Anthropic prompt caching
A8: AI cost per op (cached) | B8: ='COGS Breakdown'!D9 | C8: From COGS sheet
A9: Infra cost per op | B9: ='COGS Breakdown'!E19 | C9: From COGS sheet
A10: Blended cost per op | B10: =B8*B6+(1-B6)*B9 | C10: Weighted average
A11: Support cost per user/mo | B11: 0.5 | C11: Estimated
A12: Payment processing | B12: 0.029 | C12: Stripe 2.9% + $0.30
A15: TIER ECONOMICS
A17: Tier | B17: Monthly Price | C17: Included Ops | D17: COGS (Ops) | E17: Support | F17: Payment Proc | G17: Total COGS | H17: Gross Margin | I17: Margin %
A18: Free | B18: 0 | C18: 5000 | D18: =C18*$B$10 | E18: =$B$11 | F18: =0 | G18: =D18+E18+F18 | H18: =B18-G18 | I18: =IF(B18=0,"-",H18/B18)
A19: Personal | B19: 9 | C19: 50000 | D19: =C19*$B$10 | E19: =$B$11 | F19: =B19*$B$12+0.30 | G19: =D19+E19+F19 | H19: =B19-G19 | I19: =H19/B19
A20: Family | B20: 19 | C20: 200000 | D20: =C20*$B$10 | E20: =$B$11*2 | F20: =B20*$B$12+0.30 | G20: =D20+E20+F20 | H20: =B20-G20 | I20: =H20/B20
A21: Power (base) | B21: 29 | C21: 0 | D21: =C21*$B$10 | E21: =$B$11*2 | F21: =B21*$B$12+0.30 | G21: =D21+E21+F21 | H21: =B21-G21 | I21: =H21/B21
A24: OVERAGE ECONOMICS
A26: Tier | B26: Overage Rate/1K | C26: COGS/1K | D26: Margin/1K | E26: Margin %
A27: Personal | B27: 0.2 | C27: =$B$10*1000 | D27: =B27-C27 | E27: =D27/B27
A28: Family | B28: 0.15 | C28: =$B$10*1000 | D28: =B28-C28 | E28: =D28/B28
A29: Power | B29: 0.1 | C29: =$B$10*1000 | D29: =B29-C29 | E29: =D29/B29

Sheet Pricing Scenarios
A1: PRICING SCENARIO ANALYSIS
A3: SCENARIO A: Raise Prices to Match Competitors
A5: Tier | B5: Current | C5: Proposed | D5: Change | E5: New Margin
A6: Personal | B6: 9 | C6: 19 | D6: =C6-B6 | E6: =C6-'Unit Economics'!G19
A7: Family | B7: 19 | C7: 29 | D7: =C7-B7 | E7: =C7-'Unit Economics'!G20
A8: Power | B8: 29 | C8: 49 | D8: =C8-B8 | E8: =C8-'Unit Economics'!G21
A11: SCENARIO B: Reduce Included Operations
A13: Tier | B13: Current Ops | C13: Proposed Ops | D13: Current COGS | E13: New COGS | F13: Savings
A14: Personal | B14: 50000 | C14: 15000 | D14: ='Unit Economics'!D19 | E14: =C14*'Unit Economics'!$B$10 | F14: =D14-E14
A15: Family | B15: 200000 | C15: 50000 | D15: ='Unit Economics'!D20 | E15: =C15*'Unit Economics'!$B$10 | F15: =D15-E15
A18: SCENARIO C: RECOMMENDED HYBRID MODEL
A20: Tier | B20: Price | C20: Ops Included | D20: AI Ratio | E20: Est. COGS | F20: Gross Margin | G20: Margin %
A21: Free | B21: 0 | C21: 5000 | D21: 0.1 | E21: =C21*D21*'Unit Economics'!$B$8+C21*(1-D21)*'Unit Economics'!$B$9 | F21: =B21-E21 | G21: =IF(B21=0,"-",F21/B21)
A22: Personal | B22: 9 | C22: 25000 | D22: 0.25 | E22: =C22*D22*'Unit Economics'!$B$8+C22*(1-D22)*'Unit Economics'!$B$9 | F22: =B22-E22 | G22: =F22/B22
A23: Family | B23: 19 | C23: 75000 | D23: 0.3 | E23: =C23*D23*'Unit Economics'!$B$8+C23*(1-D23)*'Unit Economics'!$B$9 | F23: =B23-E23 | G23: =F23/B23
A24: Power | B24: 29 | C24: 0 | D24: 0 | E24: =0 | F24: =B24-E24 | G24: =F24/B24
A26: Recommended changes:
A27: • Reduce Personal ops from 50K to 25K
A28: • Reduce Family ops from 200K to 75K
A29: • Free tier gets minimal AI (10% ratio)
A30: • Power tier is pure usage-based (sustainable)

Sheet Break-Even Analysis
A1: BREAK-EVEN ANALYSIS
A3: CURRENT PRICING BREAK-EVEN
A5: Tier | B5: Revenue | C5: COGS | D5: Shortfall | E5: Overage Rate | F5: Break-even Overage Ops | G5: Total Ops for Break-even
A6: Free | B6: ='Unit Economics'!B18 | C6: ='Unit Economics'!G18 | D6: ='Unit Economics'!H18 | E6: N/A | F6: N/A | G6: N/A
A7: Personal | B7: ='Unit Economics'!B19 | C7: ='Unit Economics'!G19 | D7: ='Unit Economics'!H19 | E7: 0.2 | F7: =IF(D7<0,-D7/E7*1000,0) | G7: ='Unit Economics'!C19+F7
A8: Family | B8: ='Unit Economics'!B20 | C8: ='Unit Economics'!G20 | D8: ='Unit Economics'!H20 | E8: 0.15 | F8: =IF(D8<0,-D8/E8*1000,0) | G8: ='Unit Economics'!C20+F8
A9: Power | B9: ='Unit Economics'!B21 | C9: ='Unit Economics'!G21 | D9: ='Unit Economics'!H21 | E9: 0.1 | F9: N/A (profitable) | G9: N/A
A12: CUSTOMER LIFETIME VALUE (LTV) ANALYSIS
A14: Metric | B14: Personal | C14: Family | D14: Power
A15: Monthly Revenue | B15: 9 | C15: 19 | D15: 29
A16: Monthly COGS (est) | B16: ='Unit Economics'!G19 | C16: ='Unit Economics'!G20 | D16: ='Unit Economics'!G21
A17: Monthly Margin | B17: =B15-B16 | C17: =C15-C16 | D17: =D15-D16
A18: Churn Rate (assumed) | B18: 0.05 | C18: 0.03 | D18: 0.02
A19: Average Lifespan (mo) | B19: =1/B18 | C19: =1/C18 | D19: =1/D18
A20: LTV | B20: =B17*B19 | C20: =C17*C19 | D20: =D17*D19
A21: CAC Target (LTV/3) | B21: =B20/3 | C21: =C20/3 | D21: =D20/3

Sheet Sensitivity Analysis
A1: SENSITIVITY ANALYSIS
A3: AI COST SENSITIVITY (Personal Tier Margin)
A5: AI Ratio | B5: 10% | C5: 20% | D5: 30% | E5: 40% | F5: 50%
A6: Margin @ 25K ops | B6: =9-25000*0.1*'COGS Breakdown'!D9-25000*0.9*'COGS Breakdown'!E19 | C6: =9-25000*0.2*'COGS Breakdown'!D9-25000*0.8*'COGS Breakdown'!E19 | D6: =9-25000*0.3*'COGS Breakdown'!D9-25000*0.7*'COGS Breakdown'!E19 | E6: =9-25000*0.4*'COGS Breakdown'!D9-25000*0.6*'COGS Breakdown'!E19 | F6: =9-25000*0.5*'COGS Breakdown'!D9-25000*0.5*'COGS Breakdown'!E19
A7: Margin @ 50K ops | B7: =9-50000*0.1*'COGS Breakdown'!D9-50000*0.9*'COGS Breakdown'!E19 | C7: =9-50000*0.2*'COGS Breakdown'!D9-50000*0.8*'COGS Breakdown'!E19 | D7: =9-50000*0.3*'COGS Breakdown'!D9-50000*0.7*'COGS Breakdown'!E19 | E7: =9-50000*0.4*'COGS Breakdown'!D9-50000*0.6*'COGS Breakdown'!E19 | F7: =9-50000*0.5*'COGS Breakdown'!D9-50000*0.5*'COGS Breakdown'!E19
A10: PRICE SENSITIVITY (at 30% AI ratio, 25K ops)
A12: Price Point | B12: COGS | C12: Margin | D12: Margin %
A13: 5 | B13: =25000*0.3*'COGS Breakdown'!D9+25000*0.7*'COGS Breakdown'!E19+0.5 | C13: =A13-B13 | D13: =C13/A13
A14: 7 | B14: =25000*0.3*'COGS Breakdown'!D9+25000*0.7*'COGS Breakdown'!E19+0.5 | C14: =A14-B14 | D14: =C14/A14
A15: 9 | B15: =25000*0.3*'COGS Breakdown'!D9+25000*0.7*'COGS Breakdown'!E19+0.5 | C15: =A15-B15 | D15: =C15/A15
A16: 12 | B16: =25000*0.3*'COGS Breakdown'!D9+25000*0.7*'COGS Breakdown'!E19+0.5 | C16: =A16-B16 | D16: =C16/A16
A17: 15 | B17: =25000*0.3*'COGS Breakdown'!D9+25000*0.7*'COGS Breakdown'!E19+0.5 | C17: =A17-B17 | D17: =C17/A17
A18: 19 | B18: =25000*0.3*'COGS Breakdown'!D9+25000*0.7*'COGS Breakdown'!E19+0.5 | C18: =A18-B18 | D18: =C18/A18
A21: USAGE PATTERN SENSITIVITY
A23: Scenario | B23: Ops Used | C23: % of Included | D23: Actual COGS | E23: Effective Margin
A24: Light user | B24: 5000 | C24: =B24/25000 | D24: =B24*0.3*'COGS Breakdown'!D9 | E24: =9-D24
A25: Average user | B25: 15000 | C25: =B25/25000 | D25: =B25*0.3*'COGS Breakdown'!D9 | E25: =9-D25
A26: Heavy user | B26: 25000 | C26: =B26/25000 | D26: =B26*0.3*'COGS Breakdown'!D9 | E26: =9-D26
A27: Power user (overage) | B27: 50000 | C27: =B27/25000 | D27: =B27*0.3*'COGS Breakdown'!D9 | E27: =9+25000*0.2/1000-D27

Sheet Recommendations
A1: STRATEGIC RECOMMENDATIONS
A3: EXECUTIVE SUMMARY
A4: Current pricing is aggressive for market capture but requires careful management of AI costs and usage patterns to achieve profitability.
A6: RECOMMENDED PRICING MODEL
A8: Tier | B8: Price | C8: Ops | D8: AI Ratio | E8: Target Margin | F8: Rationale
A9: Free | B9: $0 | C9: 5,000 | D9: 10% | E9: ($1.50) | F9: Acquisition funnel
A10: Personal | B10: $9 | C10: 25,000 | D10: 25% | E10: $3-5 | F10: Value positioning vs $20 competitors
A11: Family | B11: $19 | C11: 75,000 | D11: 30% | E11: $5-8 | F11: Unique 6-member offering
A12: Power | B12: $29+usage | C12: Unlimited | D12: Any | E12: $20+ | F12: Pure margin play
A15: KEY STRATEGIES
A16: 1. OPTIMIZE AI COSTS
A17: • Implement aggressive prompt caching (target 90%+ hit rate)
A18: • Use batch API for non-time-sensitive operations (50% discount)
A19: • Route lightweight queries to smaller/cheaper models
A21: 2. CONTROL OPERATION MIX
A22: • Smart home commands should NOT trigger AI (direct execution)
A23: • Reserve AI for conversational queries only
A24: • Target: 70-80% lightweight operations
A26: 3. MONETIZE POWER USERS
A27: • Power tier at $29 base + $0.10/1K ops is highly profitable
A28: • Encourage API access upsells
... A46: SUCCESS METRICS
A48: Metric | B48: Target | C48: Timeline
A49: Blended COGS per 1K ops | B49: < $1.50 | C49: Q2 2026
A50: AI operation ratio | B50: < 30% | C50: Q1 2026
A51: Prompt cache hit rate | B51: > 90% | C51: Q1 2026
A52: Personal tier margin | B52: > $3/user/mo | C52: Q3 2026
A53: Monthly churn | B53: < 5% | C53: Q2 2026
A54: Power tier conversion | B54: > 5% of paid | C54: Q4 2026
